python_path/__init__.py
python_path-0.1.2.dist-info/DESCRIPTION.rst
python_path-0.1.2.dist-info/METADATA
python_path-0.1.2.dist-info/RECORD
python_path-0.1.2.dist-info/WHEEL
python_path-0.1.2.dist-info/metadata.json
python_path-0.1.2.dist-info/top_level.txt
