Metadata-Version: 2.0
Name: python-path
Version: 0.1.2
Summary: A clean way to import scripts on other folders via a context manager.
Home-page: https://github.com/cgarciae/python_path
Author: Cristian Garcia
Author-email: cgarcia.e88@gmail.com
License: MIT
Platform: UNKNOWN
